cligram/__init__.py
cligram/__main__.py
cligram/_paths.py
cligram/app.py
cligram/cli.py
cligram/commands/__init__.py
cligram/commands/config.py
cligram/commands/proxy.py
cligram/commands/session.py
cligram/config.py
cligram/exceptions/__init__.py
cligram/exceptions/application.py
cligram/exceptions/archive.py
cligram/exceptions/base.py
cligram/exceptions/config.py
cligram/exceptions/connection.py
cligram/exceptions/session.py
cligram/logger.py
cligram/proxy_manager.py
cligram/py.typed
cligram/scanner.py.ignore
cligram/session.py
cligram/state_manager.py
cligram/tasks/__init__.py
cligram/tasks/interactive.py
cligram/tasks/session.py
cligram/tasks/telegram.py
cligram/tasks/transfer.py
cligram/utils/__init__.py
cligram/utils/_device.cp311-win_arm64.pyd
cligram/utils/_device.pyi
cligram/utils/archive.py
cligram/utils/core.py
cligram/utils/device.py
cligram/utils/general.py
cligram/utils/telegram.py
cligram/version.py
cligram-0.4.0.dist-info/entry_points.txt
cligram-0.4.0.dist-info/licenses/LICENSE.md
cligram-0.4.0.dist-info/METADATA
cligram-0.4.0.dist-info/WHEEL
cligram-0.4.0.dist-info/RECORD
