Metadata-Version: 2.4
Name: cligram
Version: 0.4.0
Summary: cli based telegram client
License-File: LICENSE.md
Keywords: telegram,cli,bot,automation,messaging
Author: Alireza Poodineh
Author-email: itsaeliux@gmail.com
Requires-Python: <4.0,>=3.11
Classifier: Development Status :: 3 - Alpha
Classifier: Intended Audience :: Developers
Classifier: Programming Language :: Python :: 3.13
Classifier: Programming Language :: Python :: 3 :: Only
Classifier: Topic :: Communications :: Chat
Classifier: Topic :: Internet
Classifier: Typing :: Typed
Provides-Extra: speedups
Requires-Dist: aiofiles (>=25.1.0,<26.0.0)
Requires-Dist: aiohttp (>=3.8.5,<4.0.0) ; extra == "speedups"
Requires-Dist: cryptg (>=0.5.0,<0.6.0) ; extra == "speedups"
Requires-Dist: cryptography (>=46.0.3,<47.0.0)
Requires-Dist: hachoir (>=3.3.0,<4.0.0) ; extra == "speedups"
Requires-Dist: pillow (>=10.0.0,<11.0.0) ; extra == "speedups"
Requires-Dist: pysocks (>=1.7.1,<2.0.0)
Requires-Dist: python-dotenv (>=1.2.1,<2.0.0)
Requires-Dist: python-socks[asyncio] (>=2.7.2,<3.0.0)
Requires-Dist: questionary (>=2.1.1,<3.0.0)
Requires-Dist: rich (>=14.2.0,<15.0.0)
Requires-Dist: telethon (>=1.41.2,<2.0.0)
Requires-Dist: typer (>=0.20.0,<0.21.0)
Requires-Dist: ujson (>=5.8.0,<6.0.0) ; extra == "speedups"
Project-URL: Documentation, https://cligram.readthedocs.io
Project-URL: Homepage, https://github.com/Aeliux/cligram
Project-URL: Issues, https://github.com/Aeliux/cligram/issues
Project-URL: Repository, https://github.com/Aeliux/cligram
